in_pack/__init__.py
in_pack/funcs.py
tests/__init__.py
tests/test_funcs.py
in_pack-0.0.1.dist-info/METADATA
in_pack-0.0.1.dist-info/WHEEL
in_pack-0.0.1.dist-info/top_level.txt
in_pack-0.0.1.dist-info/RECORD
