Metadata-Version: 2.1
Name: in-pack
Version: 0.0.1
Summary: Python library
Author: Infinity Team
